{"metadata":{"dist-tags":{"latest":"1.0.0"},"versions":{"1.0.0":{"name":"unpipe","dist":{"tarball":"https://registry.npmjs.org/unpipe/-/unpipe-1.0.0.tgz"},"scripts":{"test":"mocha --reporter spec --bail --check-leaks test/","test-cov":"istanbul cover node_modules/mocha/bin/_mocha -- --reporter dot --check-leaks test/","test-travis":"istanbul cover node_modules/mocha/bin/_mocha --report lcovonly -- --reporter spec --check-leaks test/"}}}},"etag":"W/\"a5173aefaa90247aa242e264a76b44c9\"","lastModified":"Tue, 28 Jun 2022 05:14:31 GMT"}
